LimeSoDa/__init__.py
LimeSoDa/utils.py
LimeSoDa/data/B.204.npz
LimeSoDa/data/BB.250.npz
LimeSoDa/data/BB.30_1.npz
LimeSoDa/data/BB.30_2.npz
LimeSoDa/data/BB.51.npz
LimeSoDa/data/BB.72.npz
LimeSoDa/data/CV.98.npz
LimeSoDa/data/G.104.npz
LimeSoDa/data/G.150.npz
LimeSoDa/data/H.138.npz
LimeSoDa/data/MG.112.npz
LimeSoDa/data/MG.44.npz
LimeSoDa/data/MGS.101.npz
LimeSoDa/data/MWP.36.npz
LimeSoDa/data/NRW.115.npz
LimeSoDa/data/NRW.42.npz
LimeSoDa/data/NRW.62.npz
LimeSoDa/data/NSW.52.npz
LimeSoDa/data/O.32.npz
LimeSoDa/data/Overview_Datasets.npz
LimeSoDa/data/PC.45.npz
LimeSoDa/data/RP.62.npz
LimeSoDa/data/SA.112.npz
LimeSoDa/data/SC.50.npz
LimeSoDa/data/SC.93.npz
LimeSoDa/data/SL.125.npz
LimeSoDa/data/SM.40.npz
LimeSoDa/data/SP.231.npz
LimeSoDa/data/SSP.460.npz
LimeSoDa/data/SSP.58.npz
LimeSoDa/data/UL.120.npz
LimeSoDa/data/W.50.npz
LimeSoDa/loaders/__init__.py
limesoda-0.1.5.dist-info/licenses/LICENSE
limesoda-0.1.5.dist-info/METADATA
limesoda-0.1.5.dist-info/WHEEL
limesoda-0.1.5.dist-info/top_level.txt
limesoda-0.1.5.dist-info/RECORD
